[{"id":1,"title":"Redmi Note 5 (Gold, 64 GB)","productImage":"https://rukminim1.flixcart.com/image/550/550/jdkjzww0/mobile/d/y/b/redmi-note-5-mzb5917in-original-imaf2g8zwrmywhqq.jpeg?q=90","rating":{"average":4.4,"base":5,"ratingCount":1410,"reviewCount":2340},"pricing":{"currency":"INR","value":"11999"}},{"id":2,"title":"Apple iPhone 6 (Gold, 32 GB)","productImage":"https://rukminim1.flixcart.com/image/550/550/j6mhxu80/mobile/7/n/z/apple-iphone-6-mq3e2hn-a-original-imaexfzbdzgctzrv.jpeg?q=80","rating":{"average":4.2,"base":5,"ratingCount":5410,"reviewCount":150},"pricing":{"currency":"INR","value":"24,999"}},{"id":3,"title":"Nokia 3310 DS","productImage":"https://rukminim1.flixcart.com/image/550/550/j9338nk0/mobile/3/h/u/nokia-3310-na-original-imaevt7fsy3am2wh.jpeg?q=80","rating":{"average":4.8,"base":5,"ratingCount":9810,"reviewCount":1450},"pricing":{"currency":"INR","value":"3,250"}}]
